harmoney/__init__.py
harmoney/_callSpec.py
harmoney/client.py
harmoney/router.py
harmoney/runner.py
harmoney-0.3.0.dist-info/LICENSE
harmoney-0.3.0.dist-info/METADATA
harmoney-0.3.0.dist-info/WHEEL
harmoney-0.3.0.dist-info/top_level.txt
harmoney-0.3.0.dist-info/RECORD
