Metadata-Version: 2.2
Name: harmoney
Version: 0.3.0
Summary: Scalable Remote Function Calling Framework
Author-email: Phani Pavan K <kphanipavan@gmail.com>
License: AGPLv3
Project-URL: Homepage, https://github.com/kphanipavan/harmoney
Requires-Python: >=3.8
License-File: LICENSE
Requires-Dist: websockets>=15.0
Requires-Dist: uvicorn>=0.34.0
Requires-Dist: fastapi>=0.115.8
Requires-Dist: pydantic>=2.10.6
